qtasks/__init__.py
qtasks/__main__.py
qtasks/_state.py
qtasks/logs.py
qtasks/qtasks.py
qtasks/version.py
qtasks/asyncio/__init__.py
qtasks/asyncio/qtasks.py
qtasks/base/__init__.py
qtasks/base/qtasks.py
qtasks/brokers/__init__.py
qtasks/brokers/async_kafka.py
qtasks/brokers/async_rabbitmq.py
qtasks/brokers/async_redis.py
qtasks/brokers/async_socket.py
qtasks/brokers/base.py
qtasks/brokers/sync_kafka.py
qtasks/brokers/sync_rabbitmq.py
qtasks/brokers/sync_redis.py
qtasks/brokers/sync_socket.py
qtasks/configs/__init__.py
qtasks/configs/async_redisglobalconfig.py
qtasks/configs/base.py
qtasks/configs/config.py
qtasks/configs/sync_redisglobalconfig.py
qtasks/contexts/__init__.py
qtasks/contexts/async_context.py
qtasks/contexts/sync_context.py
qtasks/contrib/__init__.py
qtasks/contrib/django/__init__.py
qtasks/contrib/django/autodiscover.py
qtasks/contrib/redis/__init__.py
qtasks/contrib/redis/async_queue_client.py
qtasks/contrib/redis/sync_queue_client.py
qtasks/enums/__init__.py
qtasks/enums/task_status.py
qtasks/events/__init__.py
qtasks/events/async_events.py
qtasks/events/base.py
qtasks/events/events.py
qtasks/events/sync_events.py
qtasks/exc/__init__.py
qtasks/exc/plugins.py
qtasks/exc/task.py
qtasks/executors/__init__.py
qtasks/executors/async_task_executor.py
qtasks/executors/base.py
qtasks/executors/sync_task_executor.py
qtasks/middlewares/__init__.py
qtasks/middlewares/base.py
qtasks/middlewares/task.py
qtasks/mixins/plugin.py
qtasks/plugins/__init__.py
qtasks/plugins/base.py
qtasks/plugins/depends/__init__.py
qtasks/plugins/depends/async_depends.py
qtasks/plugins/depends/class_depends.py
qtasks/plugins/depends/sync_depends.py
qtasks/plugins/pydantic/__init__.py
qtasks/plugins/pydantic/async_pydantic.py
qtasks/plugins/pydantic/sync_pydantic.py
qtasks/plugins/retries/__init__.py
qtasks/plugins/retries/async_retry.py
qtasks/plugins/retries/sync_retry.py
qtasks/plugins/states/__init__.py
qtasks/plugins/states/async_state.py
qtasks/plugins/states/fsm.py
qtasks-1.6.0.dist-info/licenses/LICENSE
qtasks-1.6.0.dist-info/METADATA
qtasks-1.6.0.dist-info/WHEEL
qtasks-1.6.0.dist-info/entry_points.txt
qtasks-1.6.0.dist-info/top_level.txt
qtasks-1.6.0.dist-info/RECORD
