Metadata-Version: 2.4
Name: qtasks
Version: 1.6.0
Summary: Queue Tasks Framework
Author-email: txello <txello7@proton.me>
License: Apache-2.0
Project-URL: Homepage, https://github.com/txello/qtasks
Project-URL: Issues, https://github.com/txello/qtasks/issues
Classifier: Programming Language :: Python :: 3
Classifier: Operating System :: OS Independent
Requires-Python: >=3.10
License-File: LICENSE
Requires-Dist: typing-extensions>=4.12.2
Requires-Dist: redis>=5.2.1
Requires-Dist: anyio<4.9.0,>=4.5.0; python_version < "3.11"
Requires-Dist: anyio>=4.9.0; python_version >= "3.11"
Requires-Dist: asyncio_atexit>=1.0.1
Requires-Dist: apscheduler>=3.11.0
Requires-Dist: pydantic<2.11.7,>=2.10.6; python_version < "3.11"
Requires-Dist: pydantic>=2.11.7; python_version >= "3.11"
Provides-Extra: redis
Requires-Dist: redis>=5.2.1; extra == "redis"
Provides-Extra: rabbitmq
Requires-Dist: aio-pika>=9.5.5; extra == "rabbitmq"
Requires-Dist: pika>=1.3.2; extra == "rabbitmq"
Provides-Extra: kafka
Requires-Dist: kafka>=2.2.10; extra == "kafka"
Requires-Dist: aiokafka>=0.12.0; extra == "kafka"
Provides-Extra: test
Requires-Dist: pytest<8.4.1,>=8.3.5; python_version < "3.11" and extra == "test"
Requires-Dist: pytest>=8.4.1; python_version >= "3.11" and extra == "test"
Requires-Dist: pytest-asyncio<1.1.0,>=0.24.0; python_version < "3.11" and extra == "test"
Requires-Dist: pytest-asyncio>=1.1.0; python_version >= "3.11" and extra == "test"
Dynamic: license-file
